{
  "source": "chantsdefrance.fr",
  "total_count_site": 2801,
  "fetched_count": 2801,
  "kept_count": 2740,
  "skipped_count": 61,
  "skip_reasons": {
    "historical_book:traditions-militaires,modern_conflict": 1,
    "modern_book:foot,supporters_book:supporters-asse-6820,stadium_title_pattern": 1,
    "modern_book:foot,stadium_title_pattern": 2,
    "modern_book:xxi-eme-siecle": 12,
    "modern_book:foot": 8,
    "empty_lyrics": 14,
    "modern_book:xxi-eme-siecle,historical_book:traditions-militaires": 2,
    "club_or_supporter_text": 7,
    "modern_book:xxi-eme-siecle,year:2000": 2,
    "modern_book:xxi-eme-siecle,club_or_supporter_text,year:2013": 1,
    "year:1991": 1,
    "modern_book:xxi-eme-siecle,club_or_supporter_text": 1,
    "supporters_book:supporters-lens---rcl-4713,modern_book:foot": 1,
    "modern_book:foot,club_or_supporter_text": 2,
    "modern_book:foot,supporters_book:supporters-lens---rcl-4713,club_or_supporter_text": 1,
    "year:1977": 1,
    "year:1981": 1,
    "modern_book:foot,modern_book:foot,club_or_supporter_text": 1,
    "supporters_book:supporters-lens---rcl-4713": 1,
    "supporters_book:supporters-asse-6820": 1
  },
  "country_counts": {
    "france_fifth_republic_1958": 2038,
    "france_before_1900": 419,
    "france_third_republic_1900_1940": 238,
    "france_fourth_republic_1946_1958": 29,
    "france_vichy_1940_1944": 16
  },
  "sample_kept": [
    "136ème Pontonnier",
    "180 pucelles",
    "51 je t’aime",
    "Abal a la rébiéro",
    "A bas Bismarck et vive Boulanger!",
    "Aberriaren mugak",
    "A bientôt / Allons les amis",
    "Abmarsch in den Krieg",
    "Abmarsch ins Feld",
    "Abmarsch zur Fahne",
    "A Bordeaux",
    "Abreise aus der Heimat",
    "A Brest la jolie",
    "Abschied",
    "Abschied beim Abmarsch",
    "Abschied der Rekruten",
    "Abschied für immer",
    "Abschied im Urlaub",
    "Abschied von der Geliebten",
    "Abschied von der Kaufmanns-Mamsell"
  ],
  "sample_skipped": [
    "Afghanistan [historical_book:traditions-militaires,modern_conflict]",
    "Allez les verts [modern_book:foot,supporters_book:supporters-asse-6820,stadium_title_pattern]",
    "Allez Paris, où tu es nous sommes là [modern_book:foot,stadium_title_pattern]",
    "Amici Miei [modern_book:xxi-eme-siecle]",
    "A nos souvenirs [modern_book:xxi-eme-siecle]",
    "Askatasunera [modern_book:xxi-eme-siecle]",
    "AUX ARMES [modern_book:foot]",
    "Capitaine, capitaine [modern_book:xxi-eme-siecle]",
    "Chant du 3e Régiment de Hussards [modern_book:xxi-eme-siecle,historical_book:traditions-militaires]",
    "Chanter la mer et les marins [modern_book:xxi-eme-siecle]",
    "Chants des nains [modern_book:xxi-eme-siecle]",
    "Ciel, ciel (hymne toulonnais) [club_or_supporter_text]",
    "Debout sur la tribune [club_or_supporter_text]",
    "Echanges Auteuil/Boulogne [modern_book:foot]",
    "Hymne de la Fédération de Russie (Россия) [modern_book:xxi-eme-siecle,year:2000]",
    "Hymne du HAC [modern_book:xxi-eme-siecle,club_or_supporter_text,year:2013]",
    "Itzala [modern_book:xxi-eme-siecle,year:2000]",
    "Je chanterais jusqu’à la mort s’il le fallait [modern_book:foot]",
    "La ballade nord-irlandaise [year:1991]",
    "La complainte du poilu [modern_book:xxi-eme-siecle,historical_book:traditions-militaires]"
  ],
  "chunk_paths": [
    "out/chantsdefrance/chunks/chunk_0001.json",
    "out/chantsdefrance/chunks/chunk_0002.json",
    "out/chantsdefrance/chunks/chunk_0003.json",
    "out/chantsdefrance/chunks/chunk_0004.json",
    "out/chantsdefrance/chunks/chunk_0005.json",
    "out/chantsdefrance/chunks/chunk_0006.json",
    "out/chantsdefrance/chunks/chunk_0007.json",
    "out/chantsdefrance/chunks/chunk_0008.json",
    "out/chantsdefrance/chunks/chunk_0009.json",
    "out/chantsdefrance/chunks/chunk_0010.json",
    "out/chantsdefrance/chunks/chunk_0011.json",
    "out/chantsdefrance/chunks/chunk_0012.json",
    "out/chantsdefrance/chunks/chunk_0013.json",
    "out/chantsdefrance/chunks/chunk_0014.json",
    "out/chantsdefrance/chunks/chunk_0015.json",
    "out/chantsdefrance/chunks/chunk_0016.json",
    "out/chantsdefrance/chunks/chunk_0017.json",
    "out/chantsdefrance/chunks/chunk_0018.json",
    "out/chantsdefrance/chunks/chunk_0019.json",
    "out/chantsdefrance/chunks/chunk_0020.json",
    "out/chantsdefrance/chunks/chunk_0021.json",
    "out/chantsdefrance/chunks/chunk_0022.json",
    "out/chantsdefrance/chunks/chunk_0023.json",
    "out/chantsdefrance/chunks/chunk_0024.json",
    "out/chantsdefrance/chunks/chunk_0025.json",
    "out/chantsdefrance/chunks/chunk_0026.json",
    "out/chantsdefrance/chunks/chunk_0027.json",
    "out/chantsdefrance/chunks/chunk_0028.json",
    "out/chantsdefrance/chunks/chunk_0029.json",
    "out/chantsdefrance/chunks/chunk_0030.json",
    "out/chantsdefrance/chunks/chunk_0031.json",
    "out/chantsdefrance/chunks/chunk_0032.json",
    "out/chantsdefrance/chunks/chunk_0033.json",
    "out/chantsdefrance/chunks/chunk_0034.json",
    "out/chantsdefrance/chunks/chunk_0035.json"
  ]
}